temp_mail/__init__.py
tmp_mail/__init__.py
tmp_mail-0.1.dist-info/LICENSE
tmp_mail-0.1.dist-info/METADATA
tmp_mail-0.1.dist-info/WHEEL
tmp_mail-0.1.dist-info/top_level.txt
tmp_mail-0.1.dist-info/RECORD
