Metadata-Version: 2.1
Name: tmp-mail
Version: 0.1
Summary: Unofficial Temp-Mail.org Client
Home-page: https://github.com/KMikeeU/tmp_mail
Author: KMikeeU
Author-email: UNKNOWN
License: MIT
Platform: UNKNOWN
Requires-Dist: bs4
